orquesta_sdk/__init__.py
orquesta_sdk/base_client.py
orquesta_sdk/orquesta.py
orquesta_sdk/utils.py
orquesta_sdk/version.py
orquesta_sdk-1.8.dist-info/LICENSE
orquesta_sdk-1.8.dist-info/WHEEL
orquesta_sdk-1.8.dist-info/METADATA
orquesta_sdk-1.8.dist-info/RECORD
